pyonboard/__init__.py
pyonboard/package_data.dat
pyonboard/pyonboard.py
pyonboard-0.0.2.data/data/my_data/data_file
pyonboard-0.0.2.dist-info/DESCRIPTION.rst
pyonboard-0.0.2.dist-info/METADATA
pyonboard-0.0.2.dist-info/RECORD
pyonboard-0.0.2.dist-info/WHEEL
pyonboard-0.0.2.dist-info/entry_points.txt
pyonboard-0.0.2.dist-info/metadata.json
pyonboard-0.0.2.dist-info/top_level.txt
